rdflib_sqlalchemy/__init__.py
rdflib_sqlalchemy/store.py
rdflib_sqlalchemy/termutils.py
rdflib_sqlalchemy_redux-0.3.4.dist-info/DESCRIPTION.rst
rdflib_sqlalchemy_redux-0.3.4.dist-info/METADATA
rdflib_sqlalchemy_redux-0.3.4.dist-info/RECORD
rdflib_sqlalchemy_redux-0.3.4.dist-info/WHEEL
rdflib_sqlalchemy_redux-0.3.4.dist-info/entry_points.txt
rdflib_sqlalchemy_redux-0.3.4.dist-info/metadata.json
rdflib_sqlalchemy_redux-0.3.4.dist-info/top_level.txt
