Metadata-Version: 2.0
Name: rdflib-sqlalchemy-redux
Version: 0.3.4
Summary: rdflib extension adding SQLAlchemy as an AbstractSQLStore back-end store
Home-page: http://github.com/globality-corp/rdflib-sqlalchemy
Author: Graham Higgins, Adam Ever-Hadani
Author-email: gjhiggins@gmail.com, adamhadani@globality.com
License: BSD
Download-URL: https://github.com/globality-corp/rdflib-sqlalchemy/zipball/master
Platform: any
Classifier: Development Status :: 4 - Beta
Classifier: Programming Language :: Python
Classifier: Programming Language :: Python :: 2
Classifier: Programming Language :: Python :: 3
Classifier: Programming Language :: Python :: 2.6
Classifier: Programming Language :: Python :: 2.7
Classifier: Programming Language :: Python :: 3.3
Classifier: Programming Language :: Python :: 3.4
Classifier: Programming Language :: Python :: 3.5
Classifier: License :: OSI Approved :: BSD License
Classifier: Topic :: Software Development :: Libraries :: Python Modules
Classifier: Operating System :: OS Independent
Classifier: Natural Language :: English
Requires-Dist: SQLAlchemy
Requires-Dist: rdflib (>=4.0)
Requires-Dist: six (>=1.10.0)
